[
	{
		"EngineID": "1",
		"LanguageID": "1",
		"Name": ".com (United States)",
		"DateCreated": "2010-01-31T19:35:52.627",
		"ContryID": "234",
		"QueryURL": "https://www.google.com/search?hl=en&as_q={0}&as_epq=&as_oq=&as_eq=&num=100&lr=&as_filetype=&ft=i&as_sitesearch=&as_qdr=all&as_rights=&as_occt=any&cr=&as_nlo=&as_nhi=&safe=images",
		"ValidText": "About Google|Business Solutions|support.google.|Privacy & Terms|Send feedback|Help | google.timers.load | webcache.googleusercontent",
		"IsValid": "1",
		"DateValidated": "2015-02-14T12:08:00"
	},
	{
		"EngineID": "102",
		"LanguageID": "1255",
		"Name": ".co.il (Israel)",
		"DateCreated": "2010-09-08T11:13:58.630",
		"ContryID": "108",
		"QueryURL": "https://www.google.co.il/search?hl=iw&as_q={0}&as_epq=&as_oq=&as_eq=&num=100&lr=&as_filetype=&ft=i&as_sitesearch=&as_qdr=all&as_rights=&as_occt=any&cr=&as_nlo=&as_nhi=&safe=images",
		"ValidText": "דף הבית של Google|הכל אודות Google|support.google.|פרטיות ותנאים|שלח משוב|עזרה | google.timers.load | webcache.googleusercontent",
		"IsValid": "1",
		"DateValidated": "2015-02-14T12:08:00"
	},
	{
		"EngineID": "103",
		"LanguageID": "1",
		"Name": ".co.uk (United Kingdom)",
		"DateCreated": "2010-09-08T11:16:07.637",
		"ContryID": "233",
		"QueryURL": "https://www.google.co.uk/search?hl=en&as_q={0}&as_epq=&as_oq=&as_eq=&num=100&lr=&as_filetype=&ft=i&as_sitesearch=&as_qdr=all&as_rights=&as_occt=any&cr=&as_nlo=&as_nhi=&safe=images",
		"ValidText": "Google&nbsp;Home|Business Solutions|Google Home|support.google.|Privacy & Terms | google.timers.load | webcache.googleusercontent",
		"IsValid": "1",
		"DateValidated": "2015-02-14T12:08:00"
	},
	{
		"EngineID": "105",
		"LanguageID": "1616",
		"Name": ".com.ar (Argentina)",
		"DateCreated": "2010-09-08T11:18:51.887",
		"ContryID": "12",
		"QueryURL": "https://www.google.com.ar/search?hl=es-419&as_q={0}&as_epq=&as_oq=&as_eq=&num=100&lr=&as_filetype=&ft=i&as_sitesearch=&as_qdr=all&as_rights=&as_occt=any&cr=&as_nlo=&as_nhi=&safe=images",
		"ValidText": "Página principal de Google|Soluciones Empresariales|support.google. | google.timers.load | webcache.googleusercontent",
		"IsValid": "1",
		"DateValidated": "2015-02-14T12:09:00"
	},
	{
		"EngineID": "106",
		"LanguageID": "1",
		"Name": ".com.bd (Bangladesh)",
		"DateCreated": "2010-09-08T11:21:19.350",
		"ContryID": "16",
		"QueryURL": "https://www.google.com.bd/search?hl=bn&as_q={0}&as_epq=&as_oq=&as_eq=&num=100&lr=&as_filetype=&ft=i&as_sitesearch=&as_qdr=all&as_rights=&as_occt=any&cr=&as_nlo=&as_nhi=&safe=images",
		"ValidText": "Google&nbsp;হোম|আমাদের প্রতিক্রিয়া জানান|Google সর্ম্পকে সবকিছু|support.google. | google.timers.load | webcache.googleusercontent",
		"IsValid": "1",
		"DateValidated": "2015-02-14T12:09:00"
	},
	{
		"EngineID": "107",
		"LanguageID": "1196",
		"Name": ".ca (Canada)",
		"DateCreated": "2010-09-08T11:42:04.203",
		"ContryID": "20",
		"QueryURL": "https://www.google.ca/search?hl=en&as_q={0}&as_epq=&as_oq=&as_eq=&num=100&lr=&as_filetype=&ft=i&as_sitesearch=&as_qdr=all&as_rights=&as_occt=any&cr=&as_nlo=&as_nhi=&safe=images",
		"ValidText": "Google&nbsp;Home|Business Solutions|support.google. | google.timers.load | webcache.googleusercontent",
		"IsValid": "1",
		"DateValidated": "2015-02-14T12:09:00"
	},
	{
		"EngineID": "108",
		"LanguageID": "1301",
		"Name": ".fr (France)",
		"DateCreated": "2010-09-08T11:43:32.330",
		"ContryID": "75",
		"QueryURL": "https://www.google.fr/search?hl=fr&as_q={0}&as_epq=&as_oq=&as_eq=&num=100&lr=&as_filetype=&ft=i&as_sitesearch=&as_qdr=all&as_rights=&as_occt=any&cr=&as_nlo=&as_nhi=&safe=images",
		"ValidText": "Conseils&nbsp;de&nbsp;recherche|À propos de Google|support.google. | google.timers.load | webcache.googleusercontent",
		"IsValid": "1",
		"DateValidated": "2015-02-14T12:09:00"
	},
	{
		"EngineID": "109",
		"LanguageID": "1315",
		"Name": ".de (Germany)",
		"DateCreated": "2010-09-08T11:44:23.660",
		"ContryID": "82",
		"QueryURL": "https://www.google.de/search?hl=de&q={0}&as_epq=&as_oq=&as_eq=&num=100&lr=&as_filetype=&ft=i&as_sitesearch=&as_qdr=all&as_rights=&as_occt=any&cr=&as_nlo=&as_nhi=&safe=images",
		"ValidText": "Google-Startseite|Werben mit Google|support.google. | google.timers.load | webcache.googleusercontent",
		"IsValid": "1",
		"DateValidated": "2015-02-14T12:09:00"
	},
	{
		"EngineID": "110",
		"LanguageID": "1568",
		"Name": ".ru (Russia)",
		"DateCreated": "2010-09-08T11:44:57.667",
		"ContryID": "183",
		"QueryURL": "https://www.google.ru/search?hl=ru&q={0}&as_epq=&as_oq=&as_eq=&num=100&lr=&as_filetype=&ft=i&as_sitesearch=&as_qdr=all&as_rights=&as_occt=any&cr=&as_nlo=&as_nhi=&safe=images",
		"ValidText": "Главная страница Google&nbsp;|Рекламные программы|support.google. | google.timers.load | webcache.googleusercontent",
		"IsValid": "1",
		"DateValidated": "2015-02-14T12:09:00"
	},
	{
		"EngineID": "111",
		"LanguageID": "1368",
		"Name": ".it (Italy)",
		"DateCreated": "2010-09-08T11:45:21.707",
		"ContryID": "109",
		"QueryURL": "https://www.google.it/search?hl=it&q={0}&as_epq=&as_oq=&as_eq=&num=100&lr=&as_filetype=&ft=i&as_sitesearch=&as_qdr=all&as_rights=&as_occt=any&cr=&as_nlo=&as_nhi=&safe=images",
		"ValidText": "Home page di Google|Pubblicità|support.google. | google.timers.load | webcache.googleusercontent",
		"IsValid": "1",
		"DateValidated": "2015-02-14T12:09:00"
	},
	{
		"EngineID": "112",
		"LanguageID": "1564",
		"Name": ".ro (Romanian)",
		"DateCreated": "2010-09-08T11:46:16.467",
		"ContryID": "182",
		"QueryURL": "https://www.google.ro/search?hl=ro&q={0}&as_epq=&as_oq=&as_eq=&num=100&lr=&as_filetype=&ft=i&as_sitesearch=&as_qdr=all&as_rights=&as_occt=any&cr=&as_nlo=&as_nhi=&safe=images",
		"ValidText": "Google&nbsp;Pagină de pornire|Confidenţialitate|support.google. | google.timers.load | webcache.googleusercontent",
		"IsValid": "1",
		"DateValidated": "2015-02-14T12:09:00"
	},
	{
		"EngineID": "113",
		"LanguageID": "1274",
		"Name": ".nl (Nederland)",
		"DateCreated": "2010-09-08T11:46:46.677",
		"ContryID": "166",
		"QueryURL": "https://www.google.nl/search?hl=nl&q={0}&as_epq=&as_oq=&as_eq=&num=100&lr=&as_filetype=&ft=i&as_sitesearch=&as_qdr=all&as_rights=&as_occt=any&cr=&as_nlo=&as_nhi=&safe=images",
		"ValidText": "Google&nbsp;Startpagina|Advertentieprogramma's|support.google. | google.timers.load | webcache.googleusercontent",
		"IsValid": "1",
		"DateValidated": "2015-02-14T12:09:00"
	},
	{
		"EngineID": "114",
		"LanguageID": "1624",
		"Name": ".se (Swedish)",
		"DateCreated": "2010-09-08T11:56:06.750",
		"ContryID": "214",
		"QueryURL": "https://www.google.se/search?hl=sv&q={0}&as_epq=&as_oq=&as_eq=&num=100&lr=&as_filetype=&ft=i&as_sitesearch=&as_qdr=all&as_rights=&as_occt=any&cr=&as_nlo=&as_nhi=&safe=images",
		"ValidText": "Google&nbsp;startsida|Annonsera med Google|support.google. | google.timers.load | webcache.googleusercontent",
		"IsValid": "1",
		"DateValidated": "2015-02-14T12:09:00"
	},
	{
		"EngineID": "115",
		"LanguageID": "1261",
		"Name": ".dk (Denmark)",
		"DateCreated": "2010-09-08T11:56:45.637",
		"ContryID": "60",
		"QueryURL": "https://www.google.dk/search?hl=da&q={0}&as_epq=&as_oq=&as_eq=&num=100&lr=&as_filetype=&ft=i&as_sitesearch=&as_qdr=all&as_rights=&as_occt=any&cr=&as_nlo=&as_nhi=&safe=images",
		"ValidText": "Google&nbsp;Startside|Annoncér med Google|support.google. | google.timers.load | webcache.googleusercontent",
		"IsValid": "1",
		"DateValidated": "2015-02-14T12:09:00"
	},
	{
		"EngineID": "116",
		"LanguageID": "1297",
		"Name": ".fi (Finnish)",
		"DateCreated": "2010-09-08T12:01:59.567",
		"ContryID": "74",
		"QueryURL": "https://www.google.fi/search?hl=fi&q={0}&as_epq=&as_oq=&as_eq=&num=100&lr=&as_filetype=&ft=i&as_sitesearch=&as_qdr=all&as_rights=&as_occt=any&cr=&as_nlo=&as_nhi=&safe=images",
		"ValidText": "Google&nbsp;Etusivu|Googlen mainontaratkaisut|support.google. | google.timers.load | webcache.googleusercontent",
		"IsValid": "1",
		"DateValidated": "2015-02-14T12:09:00"
	},
	{
		"EngineID": "117",
		"LanguageID": "1552",
		"Name": ".pl (Polish)",
		"DateCreated": "2010-09-08T12:02:35.923",
		"ContryID": "177",
		"QueryURL": "https://www.google.pl/search?hl=pl&q={0}&as_epq=&as_oq=&as_eq=&num=100&lr=&as_filetype=&ft=i&as_sitesearch=&as_qdr=all&as_rights=&as_occt=any&cr=&as_nlo=&as_nhi=&safe=images",
		"ValidText": "Strona główna&nbsp;Google|Reklamuj się w Google|support.google. | google.timers.load | webcache.googleusercontent",
		"IsValid": "1",
		"DateValidated": "2015-02-14T12:09:00"
	},
	{
		"EngineID": "118",
		"LanguageID": "1508",
		"Name": ".no (Norsk)",
		"DateCreated": "2010-09-08T12:03:36.063",
		"ContryID": "166",
		"QueryURL": "https://www.google.no/search?hl=no&q={0}&as_epq=&as_oq=&as_eq=&num=100&lr=&as_filetype=&ft=i&as_sitesearch=&as_qdr=all&as_rights=&as_occt=any&cr=&as_nlo=&as_nhi=&safe=images",
		"ValidText": "Google&nbsp;Hjem|Annonsér med Google|support.google. | google.timers.load | webcache.googleusercontent",
		"IsValid": "1",
		"DateValidated": "2015-02-14T12:09:00"
	},
	{
		"EngineID": "119",
		"LanguageID": "1638",
		"Name": ".af (Afghanistan)",
		"DateCreated": "2010-09-08T12:04:45.060",
		"ContryID": "249",
		"QueryURL": "https://www.google.af/search?hl=ps&q={0}&as_epq=&as_oq=&as_eq=&num=100&lr=&as_filetype=&ft=i&as_sitesearch=&as_qdr=all&as_rights=&as_occt=any&cr=&as_nlo=&as_nhi=&safe=images",
		"ValidText": "Google&nbsp;Home|مونږ ته بیاکتنې راکړﺉ|support.google. | google.timers.load | webcache.googleusercontent",
		"IsValid": "1",
		"DateValidated": "2015-02-14T12:10:00"
	},
	{
		"EngineID": "120",
		"LanguageID": "1641",
		"Name": ".ad (Andora)",
		"DateCreated": "2010-09-08T12:05:38.673",
		"ContryID": "7",
		"QueryURL": "https://www.google.ad/search?hl=ca&q={0}&as_epq=&as_oq=&as_eq=&num=100&lr=&as_filetype=&ft=i&as_sitesearch=&as_qdr=all&as_rights=&as_occt=any&cr=&as_nlo=&as_nhi=&safe=images",
		"ValidText": "Google&nbsp;Inici|Publicitat|support.google. | google.timers.load | webcache.googleusercontent",
		"IsValid": "1",
		"DateValidated": "2015-02-14T12:10:00"
	},
	{
		"EngineID": "121",
		"LanguageID": "1161",
		"Name": ".ae (United Arab Emirates)",
		"DateCreated": "2010-09-08T12:07:30.780",
		"ContryID": "232",
		"QueryURL": "https://www.google.ae/search?hl=ar&q={0}&as_epq=&as_oq=&as_eq=&num=100&lr=&as_filetype=&ft=i&as_sitesearch=&as_qdr=all&as_rights=&as_occt=any&cr=&as_nlo=&as_nhi=&safe=images",
		"ValidText": "أرسل لنا ملاحظاتك|الخصوصية|support.google. | google.timers.load | webcache.googleusercontent",
		"IsValid": "1",
		"DateValidated": "2015-02-14T12:10:00"
	},
	{
		"EngineID": "122",
		"LanguageID": "1",
		"Name": ".ag (Antigua and Barbuda)",
		"DateCreated": "2010-09-08T12:11:00.793",
		"ContryID": "11",
		"QueryURL": "https://www.google.ag/search?hl=en&q={0}&as_epq=&as_oq=&as_eq=&num=100&lr=&as_filetype=&ft=i&as_sitesearch=&as_qdr=all&as_rights=&as_occt=any&cr=&as_nlo=&as_nhi=&safe=images",
		"ValidText": "Google&nbsp;Home|Advertising&nbsp;Programs|support.google. | google.timers.load | webcache.googleusercontent",
		"IsValid": "1",
		"DateValidated": "2015-02-14T12:11:00"
	},
	{
		"EngineID": "123",
		"LanguageID": "1642",
		"Name": ".com (Albania)",
		"DateCreated": "2010-09-08T12:12:53.277",
		"ContryID": "4",
		"QueryURL": "https://www.google.com/search?hl=sq&q={0}&as_epq=&as_oq=&as_eq=&num=100&lr=&as_filetype=&ft=i&as_sitesearch=&as_qdr=all&as_rights=&as_occt=any&cr=&as_nlo=&as_nhi=&safe=images",
		"ValidText": "Udhëzime për Kërkim|Na jepni reagimin (komentet) tuaja|Gjithcka per Google|support.google. | google.timers.load | webcache.googleusercontent",
		"IsValid": "1",
		"DateValidated": "2015-02-14T12:11:00"
	},
	{
		"EngineID": "124",
		"LanguageID": "1643",
		"Name": ".am (Armenia)",
		"DateCreated": "2010-09-08T12:13:47.240",
		"ContryID": "13",
		"QueryURL": "https://www.google.am/search?hl=hy&q={0}&as_epq=&as_oq=&as_eq=&num=100&lr=&as_filetype=&ft=i&as_sitesearch=&as_qdr=all&as_rights=&as_occt=any&cr=&as_nlo=&as_nhi=&safe=images",
		"ValidText": "Փնտրահուշում|Ամենը Google-ի մասին|support.google. | google.timers.load | webcache.googleusercontent",
		"IsValid": "1",
		"DateValidated": "2015-02-14T12:11:00"
	},
	{
		"EngineID": "125",
		"LanguageID": "1553",
		"Name": ".co.ao (Angola)",
		"DateCreated": "2010-09-08T12:14:57.700",
		"ContryID": "9",
		"QueryURL": "https://www.google.co.ao/search?hl=pt-PT&q={0}&as_epq=&as_oq=&as_eq=&num=100&lr=&as_filetype=&ft=i&as_sitesearch=&as_qdr=all&as_rights=&as_occt=any&cr=&as_nlo=&as_nhi=&safe=images",
		"ValidText": "Google&nbsp;Página inicial|Envie-nos os seus comentários|support.google. | google.timers.load | webcache.googleusercontent",
		"IsValid": "1",
		"DateValidated": "2015-02-14T12:12:00"
	},
	{
		"EngineID": "126",
		"LanguageID": "1315",
		"Name": ".at (Austria)",
		"DateCreated": "2010-09-08T12:17:10.597",
		"ContryID": "16",
		"QueryURL": "https://www.google.at/search?hl=de&q={0}&as_epq=&as_oq=&as_eq=&num=100&lr=&as_filetype=&ft=i&as_sitesearch=&as_qdr=all&as_rights=&as_occt=any&cr=&as_nlo=&as_nhi=&safe=images",
		"ValidText": "Google-Startseite|Werben mit Google|support.google. | google.timers.load | webcache.googleusercontent",
		"IsValid": "1",
		"DateValidated": "2015-02-14T12:12:00"
	},
	{
		"EngineID": "127",
		"LanguageID": "1644",
		"Name": ".az (Azerbaijan)",
		"DateCreated": "2010-09-08T12:18:03.333",
		"ContryID": "17",
		"QueryURL": "https://www.google.az/search?hl=az&q={0}&as_epq=&as_oq=&as_eq=&num=100&lr=&as_filetype=&ft=i&as_sitesearch=&as_qdr=all&as_rights=&as_occt=any&cr=&as_nlo=&as_nhi=&safe=images",
		"ValidText": "Axtarış üçün Göstərişlər|Google haqqında hər şey|support.google. | google.timers.load | webcache.googleusercontent",
		"IsValid": "1",
		"DateValidated": "2015-02-14T12:12:00"
	},
	{
		"EngineID": "128",
		"LanguageID": "1586",
		"Name": ".ba (Bosnia and Herzegovina)",
		"DateCreated": "2010-09-08T12:21:26.363",
		"ContryID": "29",
		"QueryURL": "https://www.google.ba/search?hl=bs&q={0}&as_epq=&as_oq=&as_eq=&num=100&lr=&as_filetype=&ft=i&as_sitesearch=&as_qdr=all&as_rights=&as_occt=any&cr=&as_nlo=&as_nhi=&safe=images",
		"ValidText": "Google&nbsp;Home|Sve o Googleu|Pošaljite nam vaše mišljenje|support.google. | google.timers.load | webcache.googleusercontent",
		"IsValid": "1",
		"DateValidated": "2015-02-14T12:12:00"
	},
	{
		"EngineID": "129",
		"LanguageID": "1315",
		"Name": ".be (Belgium)",
		"DateCreated": "2010-09-08T12:22:41.033",
		"ContryID": "23",
		"QueryURL": "https://www.google.be/search?hl=nl&q={0}&as_epq=&as_oq=&as_eq=&num=100&lr=&as_filetype=&ft=i&as_sitesearch=&as_qdr=all&as_rights=&as_occt=any&cr=&as_nlo=&as_nhi=&safe=images",
		"ValidText": "Google&nbsp;Startpagina|Advertentieprogramma's|support.google. | google.timers.load | webcache.googleusercontent",
		"IsValid": "1",
		"DateValidated": "2015-02-14T12:12:00"
	},
	{
		"EngineID": "130",
		"LanguageID": "1213",
		"Name": ".bg (Bulgarian)",
		"DateCreated": "2010-09-08T12:23:13.310",
		"ContryID": "35",
		"QueryURL": "https://www.google.bg/search?hl=bg&q={0}&as_epq=&as_oq=&as_eq=&num=100&lr=&as_filetype=&ft=i&as_sitesearch=&as_qdr=all&as_rights=&as_occt=any&cr=&as_nlo=&as_nhi=&safe=images",
		"ValidText": "Google&nbsp;Начална страница|Изпратете ни отзиви|support.google. | google.timers.load | webcache.googleusercontent",
		"IsValid": "1",
		"DateValidated": "2015-02-14T12:12:00"
	},
	{
		"EngineID": "131",
		"LanguageID": "1161",
		"Name": ".bh (Bahrain)",
		"DateCreated": "2010-09-08T12:24:57.763",
		"ContryID": "19",
		"QueryURL": "https://www.google.com.bh/search?hl=ar&q={0}&as_epq=&as_oq=&as_eq=&num=100&lr=&as_filetype=&ft=i&as_sitesearch=&as_qdr=all&as_rights=&as_occt=any&cr=&as_nlo=&as_nhi=&safe=images",
		"ValidText": "نصائح للبحث|الخصوصية|support.google. | google.timers.load | webcache.googleusercontent",
		"IsValid": "1",
		"DateValidated": "2015-02-14T12:12:00"
	},
	{
		"EngineID": "132",
		"LanguageID": "1301",
		"Name": ".bi (Burundi)",
		"DateCreated": "2010-09-08T12:27:59.303",
		"ContryID": "37",
		"QueryURL": "https://www.google.bi/search?hl=fr&q={0}&as_epq=&as_oq=&as_eq=&num=100&lr=&as_filetype=&ft=i&as_sitesearch=&as_qdr=all&as_rights=&as_occt=any&cr=&as_nlo=&as_nhi=&safe=images",
		"ValidText": "Accueil&nbsp;Google|Programmes de publicité|support.google. | google.timers.load | webcache.googleusercontent",
		"IsValid": "1",
		"DateValidated": "2015-02-14T12:12:00"
	},
	{
		"EngineID": "133",
		"LanguageID": "1301",
		"Name": ".bo (Benin)",
		"DateCreated": "2010-09-08T12:29:36.740",
		"ContryID": "25",
		"QueryURL": "https://www.google.com.bo/search?hl=es&q={0}&as_epq=&as_oq=&as_eq=&num=100&lr=&as_filetype=&ft=i&as_sitesearch=&as_qdr=all&as_rights=&as_occt=any&cr=&as_nlo=&as_nhi=&safe=images",
		"ValidText": "Página principal de&nbsp;Google|Soluciones Empresariales|support.google. | google.timers.load | webcache.googleusercontent",
		"IsValid": "1",
		"DateValidated": "2015-02-14T12:12:00"
	},
	{
		"EngineID": "134",
		"LanguageID": "1616",
		"Name": ".br (Bolivia)",
		"DateCreated": "2010-09-08T12:30:39.830",
		"ContryID": "28",
		"QueryURL": "https://www.google.com.br/search?hl=pt-BR&q={0}&as_epq=&as_oq=&as_eq=&num=100&lr=&as_filetype=&ft=i&as_sitesearch=&as_qdr=all&as_rights=&as_occt=any&cr=&as_nlo=&as_nhi=&safe=images",
		"ValidText": "Página inicial do&nbsp;Google|Soluções de publicidade|support.google. | google.timers.load | webcache.googleusercontent",
		"IsValid": "1",
		"DateValidated": "2015-02-14T12:13:00"
	},
	{
		"EngineID": "135",
		"LanguageID": "1553",
		"Name": ".com.br (Brazil)",
		"DateCreated": "2010-09-08T12:31:29.070",
		"ContryID": "32",
		"QueryURL": "https://www.google.bs/search?hl=en&q={0}&as_epq=&as_oq=&as_eq=&num=100&lr=&as_filetype=&ft=i&as_sitesearch=&as_qdr=all&as_rights=&as_occt=any&cr=&as_nlo=&as_nhi=&safe=images",
		"ValidText": "Google&nbsp;Home|Advertising&nbsp;Programs|support.google. | google.timers.load | webcache.googleusercontent",
		"IsValid": "1",
		"DateValidated": "2015-02-14T12:13:00"
	},
	{
		"EngineID": "136",
		"LanguageID": "1",
		"Name": ".bs (Bahamas)",
		"DateCreated": "2010-09-08T12:33:01.520",
		"ContryID": "18",
		"QueryURL": "https://www.google.bs/search?hl=en&q={0}&as_epq=&as_oq=&as_eq=&num=100&lr=&as_filetype=&ft=i&as_sitesearch=&as_qdr=all&as_rights=&as_occt=any&cr=&as_nlo=&as_nhi=&safe=images",
		"ValidText": "Search Help|Give us feedback|About Google|Google&nbsp;Home|support.google. | google.timers.load | webcache.googleusercontent",
		"IsValid": "1",
		"DateValidated": "2015-02-14T12:13:00"
	},
	{
		"EngineID": "137",
		"LanguageID": "1645",
		"Name": ".com.by (Belarus)",
		"DateCreated": "2010-09-08T12:34:24.933",
		"ContryID": "22",
		"QueryURL": "https://www.google.com.by/search?hl=be&q={0}&as_epq=&as_oq=&as_eq=&num=100&lr=&as_filetype=&ft=i&as_sitesearch=&as_qdr=all&as_rights=&as_occt=any&cr=&as_nlo=&as_nhi=&safe=images",
		"ValidText": "Пошукавыя падказкі|Усё пра Google|support.google. | google.timers.load | webcache.googleusercontent",
		"IsValid": "1",
		"DateValidated": "2015-02-14T12:13:00"
	},
	{
		"EngineID": "138",
		"LanguageID": "1646",
		"Name": ".cd (Congo)",
		"DateCreated": "2010-09-08T12:35:46.530",
		"ContryID": "51",
		"QueryURL": "https://www.google.cd/search?hl=fr&q={0}&as_epq=&as_oq=&as_eq=&num=100&lr=&as_filetype=&ft=i&as_sitesearch=&as_qdr=all&as_rights=&as_occt=any&cr=&as_nlo=&as_nhi=&safe=images",
		"ValidText": "Accueil&nbsp;Google|Programmes de publicité|support.google. | google.timers.load | webcache.googleusercontent",
		"IsValid": "1",
		"DateValidated": "2015-02-14T12:13:00"
	},
	{
		"EngineID": "139",
		"LanguageID": "1624",
		"Name": ".ch (Switzerland)",
		"DateCreated": "2010-09-08T12:37:24.340",
		"ContryID": "212",
		"QueryURL": "https://www.google.ch/search?hl=de&q={0}&as_epq=&as_oq=&as_eq=&num=100&lr=&as_filetype=&ft=i&as_sitesearch=&as_qdr=all&as_rights=&as_occt=any&cr=&as_nlo=&as_nhi=&safe=images",
		"ValidText": "Google-Startseite|Werben mit Google|support.google. | google.timers.load | webcache.googleusercontent",
		"IsValid": "1",
		"DateValidated": "2015-02-14T12:13:00"
	},
	{
		"EngineID": "141",
		"LanguageID": "1",
		"Name": ".cl (Chile)",
		"DateCreated": "2010-09-08T12:39:25.463",
		"ContryID": "45",
		"QueryURL": "https://www.google.cl/search?hl=es&q={0}&as_epq=&as_oq=&as_eq=&num=100&lr=&as_filetype=&ft=i&as_sitesearch=&as_qdr=all&as_rights=&as_occt=any&cr=&as_nlo=&as_nhi=&safe=images",
		"ValidText": "Página principal de&nbsp;Google|Programas de publicidad|support.google. | google.timers.load | webcache.googleusercontent",
		"IsValid": "1",
		"DateValidated": "2015-02-14T12:13:00"
	},
	{
		"EngineID": "142",
		"LanguageID": "1616",
		"Name": ".com.co (Colombia)",
		"DateCreated": "2010-09-08T12:40:09.563",
		"ContryID": "49",
		"QueryURL": "https://www.google.com.co/search?hl=es&q={0}&as_epq=&as_oq=&as_eq=&num=100&lr=&as_filetype=&ft=i&as_sitesearch=&as_qdr=all&as_rights=&as_occt=any&cr=&as_nlo=&as_nhi=&safe=images",
		"ValidText": "Página principal de&nbsp;Google|Programas de publicidad|support.google. | google.timers.load | webcache.googleusercontent",
		"IsValid": "1",
		"DateValidated": "2015-02-14T12:13:00"
	},
	{
		"EngineID": "143",
		"LanguageID": "1616",
		"Name": ".com.cu (Cuba)",
		"DateCreated": "2010-09-08T12:41:17.120",
		"ContryID": "57",
		"QueryURL": "https://www.google.com.cu/search?hl=es&q={0}&as_epq=&as_oq=&as_eq=&num=100&lr=&as_filetype=&ft=i&as_sitesearch=&as_qdr=all&as_rights=&as_occt=any&cr=&as_nlo=&as_nhi=&safe=images",
		"ValidText": "Página principal de&nbsp;Google|Enviar comentarios|support.google. | google.timers.load | webcache.googleusercontent",
		"IsValid": "1",
		"DateValidated": "2015-02-14T12:13:00"
	},
	{
		"EngineID": "144",
		"LanguageID": "1259",
		"Name": ".cz (Czech Republic)",
		"DateCreated": "2010-09-08T12:42:00.380",
		"ContryID": "59",
		"QueryURL": "https://www.google.cz/search?hl=cs&q={0}&as_epq=&as_oq=&as_eq=&num=100&lr=&as_filetype=&ft=i&as_sitesearch=&as_qdr=all&as_rights=&as_occt=any&cr=&as_nlo=&as_nhi=&safe=images",
		"ValidText": "Domovská stránka Google&nbsp;|Inzerujte s Googlem|support.google. | google.timers.load | webcache.googleusercontent",
		"IsValid": "1",
		"DateValidated": "2015-02-14T12:13:00"
	},
	{
		"EngineID": "145",
		"LanguageID": "1616",
		"Name": ".com.do (Dominican Republic)",
		"DateCreated": "2010-09-08T12:47:32.117",
		"ContryID": "63",
		"QueryURL": "https://www.google.com.do/search?hl=es&q={0}&as_epq=&as_oq=&as_eq=&num=100&lr=&as_filetype=&ft=i&as_sitesearch=&as_qdr=all&as_rights=&as_occt=any&cr=&as_nlo=&as_nhi=&safe=images",
		"ValidText": "Página principal de&nbsp;Google|Soluciones Empresariales|support.google. | google.timers.load | webcache.googleusercontent",
		"IsValid": "1",
		"DateValidated": "2015-02-14T12:13:00"
	},
	{
		"EngineID": "146",
		"LanguageID": "1616",
		"Name": ".com.ec (Ecuador)",
		"DateCreated": "2010-09-08T12:49:08.783",
		"ContryID": "64",
		"QueryURL": "https://www.google.com.ec/search?hl=es&q={0}&as_epq=&as_oq=&as_eq=&num=100&lr=&as_filetype=&ft=i&as_sitesearch=&as_qdr=all&as_rights=&as_occt=any&cr=&as_nlo=&as_nhi=&safe=images",
		"ValidText": "Página principal de&nbsp;Google|Soluciones Empresariales|support.google. | google.timers.load | webcache.googleusercontent",
		"IsValid": "1",
		"DateValidated": "2015-02-14T12:13:00"
	},
	{
		"EngineID": "147",
		"LanguageID": "1647",
		"Name": ".ee (Estonia)",
		"DateCreated": "2010-09-08T12:49:54.900",
		"ContryID": "69",
		"QueryURL": "https://www.google.ee/search?hl=et&q={0}&as_epq=&as_oq=&as_eq=&num=100&lr=&as_filetype=&ft=i&as_sitesearch=&as_qdr=all&as_rights=&as_occt=any&cr=&as_nlo=&as_nhi=&safe=images",
		"ValidText": "Google&nbsp;Kodu|Privaatsus|support.google. | google.timers.load | webcache.googleusercontent",
		"IsValid": "1",
		"DateValidated": "2015-02-14T12:13:00"
	},
	{
		"EngineID": "148",
		"LanguageID": "1161",
		"Name": ".com.eg (Egypt)",
		"DateCreated": "2010-09-08T12:50:52.990",
		"ContryID": "65",
		"QueryURL": "https://www.google.com.eg/search?hl=ar&q={0}&as_epq=&as_oq=&as_eq=&num=100&lr=&as_filetype=&ft=i&as_sitesearch=&as_qdr=all&as_rights=&as_occt=any&cr=&as_nlo=&as_nhi=&safe=images",
		"ValidText": "أرسل لنا ملاحظاتك|أرسل لنا ملاحظاتك|الخصوصية|support.google. | google.timers.load | webcache.googleusercontent",
		"IsValid": "1",
		"DateValidated": "2015-02-14T12:13:00"
	},
	{
		"EngineID": "149",
		"LanguageID": "1616",
		"Name": ".es (Spain)",
		"DateCreated": "2010-09-08T12:55:28.863",
		"ContryID": "207",
		"QueryURL": "https://www.google.es/search?hl=es&q={0}&as_epq=&as_oq=&as_eq=&num=100&lr=&as_filetype=&ft=i&as_sitesearch=&as_qdr=all&as_rights=&as_occt=any&cr=&as_nlo=&as_nhi=&safe=images",
		"ValidText": "Página principal de&nbsp;Google|Programas de publicidad|support.google. | google.timers.load | webcache.googleusercontent",
		"IsValid": "1",
		"DateValidated": "2015-02-14T12:13:00"
	},
	{
		"EngineID": "150",
		"LanguageID": "1649",
		"Name": ".ge (Georgia)",
		"DateCreated": "2010-09-08T12:57:09.123",
		"ContryID": "81",
		"QueryURL": "https://www.google.ge/search?hl=ka&q={0}&as_epq=&as_oq=&as_eq=&num=100&lr=&as_filetype=&ft=i&as_sitesearch=&as_qdr=all&as_rights=&as_occt=any&cr=&as_nlo=&as_nhi=&safe=images",
		"ValidText": "ძებნის ხერხები|მოგვწერეთ|Google&nbsp;Home|მოგვწერეთ|support.google. | google.timers.load | webcache.googleusercontent",
		"IsValid": "1",
		"DateValidated": "2015-02-14T12:14:00"
	},
	{
		"EngineID": "151",
		"LanguageID": "1650",
		"Name": ".gl (Greenland)",
		"DateCreated": "2010-09-08T12:58:33.680",
		"ContryID": "86",
		"QueryURL": "https://www.google.gl/search?hl=da&q={0}&as_epq=&as_oq=&as_eq=&num=100&lr=&as_filetype=&ft=i&as_sitesearch=&as_qdr=all&as_rights=&as_occt=any&cr=&as_nlo=&as_nhi=&safe=images",
		"ValidText": "Google&nbsp;Startside|Fortrolighed|support.google. | google.timers.load | webcache.googleusercontent",
		"IsValid": "1",
		"DateValidated": "2015-02-14T12:14:00"
	},
	{
		"EngineID": "152",
		"LanguageID": "1327",
		"Name": ".gr (Greece)",
		"DateCreated": "2010-09-08T13:00:35.163",
		"ContryID": "85",
		"QueryURL": "https://www.google.gr/search?hl=el&q={0}&as_epq=&as_oq=&as_eq=&num=100&lr=&as_filetype=&ft=i&as_sitesearch=&as_qdr=all&as_rights=&as_occt=any&cr=&as_nlo=&as_nhi=&safe=images",
		"ValidText": "Google&nbsp;Αρχική σελίδα|Στείλτε μας τα σχόλιά σας|support.google. | google.timers.load | webcache.googleusercontent",
		"IsValid": "1",
		"DateValidated": "2015-02-14T12:14:00"
	},
	{
		"EngineID": "153",
		"LanguageID": "1616",
		"Name": ".com.gt (Guatemala)",
		"DateCreated": "2010-09-08T14:25:00.093",
		"ContryID": "90",
		"QueryURL": "https://www.google.com.gt/search?hl=es&q={0}&as_epq=&as_oq=&as_eq=&num=100&lr=&as_filetype=&ft=i&as_sitesearch=&as_qdr=all&as_rights=&as_occt=any&cr=&as_nlo=&as_nhi=&safe=images",
		"ValidText": "Página principal de&nbsp;Google|Soluciones Empresariales|support.google. | google.timers.load | webcache.googleusercontent",
		"IsValid": "1",
		"DateValidated": "2015-02-14T12:14:00"
	},
	{
		"EngineID": "154",
		"LanguageID": "1233",
		"Name": ".com.hk (Hong Kong)",
		"DateCreated": "2010-09-08T14:25:57.707",
		"ContryID": "99",
		"QueryURL": "https://www.google.com.hk/search?hl=zh-TW&q={0}&as_epq=&as_oq=&as_eq=&num=100&lr=&as_filetype=&ft=i&as_sitesearch=&as_qdr=all&as_rights=&as_occt=any&cr=&as_nlo=&as_nhi=&safe=images",
		"ValidText": "廣告服務|隱私權政策|support.google. | google.timers.load | webcache.googleusercontent",
		"IsValid": "1",
		"DateValidated": "2015-02-14T12:14:00"
	},
	{
		"EngineID": "155",
		"LanguageID": "1616",
		"Name": ".com.hn (Honduras)",
		"DateCreated": "2010-09-08T14:26:40.923",
		"ContryID": "98",
		"QueryURL": "https://www.google.hn/search?hl=es&q={0}&as_epq=&as_oq=&as_eq=&num=100&lr=&as_filetype=&ft=i&as_sitesearch=&as_qdr=all&as_rights=&as_occt=any&cr=&as_nlo=&as_nhi=&safe=images",
		"ValidText": "Página principal de&nbsp;Google|Soluciones Empresariales|support.google. | google.timers.load | webcache.googleusercontent",
		"IsValid": "1",
		"DateValidated": "2015-02-14T12:14:00"
	},
	{
		"EngineID": "156",
		"LanguageID": "1257",
		"Name": ".com.hr (Croatia)",
		"DateCreated": "2010-09-08T14:28:47.057",
		"ContryID": "56",
		"QueryURL": "https://www.google.hr/search?hl=hr&q={0}&as_epq=&as_oq=&as_eq=&num=100&lr=&as_filetype=&ft=i&as_sitesearch=&as_qdr=all&as_rights=&as_occt=any&cr=&as_nlo=&as_nhi=&safe=images",
		"ValidText": "Google&nbsp;početna stranica|Sve o Googleu|support.google. | google.timers.load | webcache.googleusercontent",
		"IsValid": "1",
		"DateValidated": "2015-02-14T12:14:00"
	},
	{
		"EngineID": "157",
		"LanguageID": "1301",
		"Name": ".ht (Haiti)",
		"DateCreated": "2010-09-08T14:29:30.120",
		"ContryID": "95",
		"QueryURL": "https://www.google.ht/search?hl=fr&q={0}&as_epq=&as_oq=&as_eq=&num=100&lr=&as_filetype=&ft=i&as_sitesearch=&as_qdr=all&as_rights=&as_occt=any&cr=&as_nlo=&as_nhi=&safe=images",
		"ValidText": "Programmes de publicité|Confidentialité|support.google. | google.timers.load | webcache.googleusercontent",
		"IsValid": "1",
		"DateValidated": "2015-02-14T12:14:00"
	},
	{
		"EngineID": "158",
		"LanguageID": "1345",
		"Name": ".hu (Hungary)",
		"DateCreated": "2010-09-08T14:30:33.607",
		"ContryID": "100",
		"QueryURL": "https://www.google.hu/search?hl=hu&q={0}&as_epq=&as_oq=&as_eq=&num=100&lr=&as_filetype=&ft=i&as_sitesearch=&as_qdr=all&as_rights=&as_occt=any&cr=&as_nlo=&as_nhi=&safe=images",
		"ValidText": "Google&nbsp;főoldal|Rólunk|support.google. | google.timers.load | webcache.googleusercontent",
		"IsValid": "1",
		"DateValidated": "2015-02-14T12:14:00"
	},
	{
		"EngineID": "159",
		"LanguageID": "1357",
		"Name": ".co.id (Indonesia)",
		"DateCreated": "2010-09-08T14:31:31.557",
		"ContryID": "103",
		"QueryURL": "https://www.google.co.id/search?id=en&hl=id&q={0}&as_epq=&as_oq=&as_eq=&num=100&lr=&as_filetype=&ft=i&as_sitesearch=&as_qdr=all&as_rights=&as_occt=any&cr=&as_nlo=&as_nhi=&safe=images",
		"ValidText": "Cara cara kanggo nggolekki kanthi bener|Beranda&nbsp;Google|Serba-serbi Google|support.google. | google.timers.load | webcache.googleusercontent",
		"IsValid": "1",
		"DateValidated": "2015-02-14T12:14:00"
	},
	{
		"EngineID": "160",
		"LanguageID": "1639",
		"Name": ".ie (Ireland)",
		"DateCreated": "2010-09-08T14:32:20.577",
		"ContryID": "106",
		"QueryURL": "https://www.google.ie/search?hl=ga&q={0}&as_epq=&as_oq=&as_eq=&num=100&lr=&as_filetype=&ft=i&as_sitesearch=&as_qdr=all&as_rights=&as_occt=any&cr=&as_nlo=&as_nhi=&safe=images",
		"ValidText": "Leideanna&nbsp;Cuardaigh|Tabhair aiseolas dhúinn|Google&nbsp;Home|An tEolas ar Fad faoi Google|support.google. | google.timers.load | webcache.googleusercontent",
		"IsValid": "1",
		"DateValidated": "2015-02-14T12:14:00"
	},
	{
		"EngineID": "161",
		"LanguageID": "1341",
		"Name": ".co.in (India)",
		"DateCreated": "2010-09-08T14:33:11.680",
		"ContryID": "102",
		"QueryURL": "https://www.google.co.in/search?hl=hi&q={0}&as_epq=&as_oq=&as_eq=&num=100&lr=&as_filetype=&ft=i&as_sitesearch=&as_qdr=all&as_rights=&as_occt=any&cr=&as_nlo=&as_nhi=&safe=images",
		"ValidText": "खोज-सुझाव|हमें फ़ीडबैक दें|Google&nbsp;मुखपृष्ठ|खोज-सुझाव|हमें फ़ीडबैक दें|support.google. | google.timers.load | webcache.googleusercontent",
		"IsValid": "1",
		"DateValidated": "2015-02-14T12:14:00"
	},
	{
		"EngineID": "162",
		"LanguageID": "1315",
		"Name": ".is (Iceland)",
		"DateCreated": "2010-09-08T14:33:58.943",
		"ContryID": "101",
		"QueryURL": "https://www.google.is/search?hl=is&q={0}&as_epq=&as_oq=&as_eq=&num=100&lr=&as_filetype=&ft=i&as_sitesearch=&as_qdr=all&as_rights=&as_occt=any&cr=&as_nlo=&as_nhi=&safe=images",
		"ValidText": "Leitarheilræði|Auglýsingar|Google&nbsp;Heim|support.google. | google.timers.load | webcache.googleusercontent",
		"IsValid": "1",
		"DateValidated": "2015-02-14T12:14:00"
	},
	{
		"EngineID": "163",
		"LanguageID": "1",
		"Name": ".com.jm (Jamaica)",
		"DateCreated": "2010-09-08T14:34:52.833",
		"ContryID": "110",
		"QueryURL": "https://www.google.com.jm/search?hl=en&q={0}&as_epq=&as_oq=&as_eq=&num=100&lr=&as_filetype=&ft=i&as_sitesearch=&as_qdr=all&as_rights=&as_occt=any&cr=&as_nlo=&as_nhi=&safe=images",
		"ValidText": "Google&nbsp;Home|About Google|support.google. | google.timers.load | webcache.googleusercontent",
		"IsValid": "1",
		"DateValidated": "2015-02-14T12:14:00"
	},
	{
		"EngineID": "164",
		"LanguageID": "1161",
		"Name": ".jo (Jordan)",
		"DateCreated": "2010-09-08T14:35:40.807",
		"ContryID": "113",
		"QueryURL": "https://www.google.jo/search?hl=ar&q={0}&as_epq=&as_oq=&as_eq=&num=100&lr=&as_filetype=&ft=i&as_sitesearch=&as_qdr=all&as_rights=&as_occt=any&cr=&as_nlo=&as_nhi=&safe=images",
		"ValidText": "الخصوصية|كل ما تحب معرفته عن Google&rlm; هنا|الخصوصية|support.google. | google.timers.load | webcache.googleusercontent",
		"IsValid": "1",
		"DateValidated": "2015-02-14T12:14:00"
	},
	{
		"EngineID": "165",
		"LanguageID": "1369",
		"Name": ".co.jp (Japan)",
		"DateCreated": "2010-09-08T14:36:27.507",
		"ContryID": "111",
		"QueryURL": "https://www.google.co.jp/search?hl=ja&q={0}&as_epq=&as_oq=&as_eq=&num=100&lr=&as_filetype=&ft=i&as_sitesearch=&as_qdr=all&as_rights=&as_occt=any&cr=&as_nlo=&as_nhi=&safe=images",
		"ValidText": "広告掲載|Google&nbsp;ホーム|ヘルプ|support.google. | google.timers.load | webcache.googleusercontent",
		"IsValid": "1",
		"DateValidated": "2015-02-14T12:15:00"
	},
	{
		"EngineID": "166",
		"LanguageID": "1",
		"Name": ".co.ke (Kenya)",
		"DateCreated": "2010-09-08T14:37:16.450",
		"ContryID": "115",
		"QueryURL": "https://www.google.co.ke/search?hl=sw&q={0}&as_epq=&as_oq=&as_eq=&num=100&lr=&as_filetype=&ft=i&as_sitesearch=&as_qdr=all&as_rights=&as_occt=any&cr=&as_nlo=&as_nhi=&safe=images",
		"ValidText": "Vidokezo&nbsp;vya Utafutaji|Google&nbsp;Nyumbani|Kila Kitu|support.google. | google.timers.load | webcache.googleusercontent",
		"IsValid": "1",
		"DateValidated": "2015-02-14T12:15:00"
	},
	{
		"EngineID": "167",
		"LanguageID": "1640",
		"Name": ".kg (Kyrgyzstan)",
		"DateCreated": "2010-09-08T14:38:05.480",
		"ContryID": "120",
		"QueryURL": "https://www.google.kg/search?hl=ky&q={0}&as_epq=&as_oq=&as_eq=&num=100&lr=&as_filetype=&ft=i&as_sitesearch=&as_qdr=all&as_rights=&as_occt=any&cr=&as_nlo=&as_nhi=&safe=images",
		"ValidText": "Издөө шыбыроолору|Google жөнүндө|Баары|Google&nbsp;Home|support.google. | google.timers.load | webcache.googleusercontent",
		"IsValid": "1",
		"DateValidated": "2015-02-14T12:15:00"
	},
	{
		"EngineID": "168",
		"LanguageID": "1651",
		"Name": ".com.kh (Cambodia)",
		"DateCreated": "2010-09-08T14:39:00.277",
		"ContryID": "38",
		"QueryURL": "https://www.google.com.kh/search?hl=km&q={0}&as_epq=&as_oq=&as_eq=&num=100&lr=&as_filetype=&ft=i&as_sitesearch=&as_qdr=all&as_rights=&as_occt=any&cr=&as_nlo=&as_nhi=&safe=images",
		"ValidText": "គន្លឹះសំរាប់ការស្វែងរក|Google&nbsp;Home|support.google. | google.timers.load | webcache.googleusercontent",
		"IsValid": "1",
		"DateValidated": "2015-02-14T12:15:00"
	},
	{
		"EngineID": "169",
		"LanguageID": "1404",
		"Name": ".co.kr (South Korea)",
		"DateCreated": "2010-09-08T14:39:49.840",
		"ContryID": "118",
		"QueryURL": "https://www.google.co.kr/search?hl=ko&q={0}&as_epq=&as_oq=&as_eq=&num=100&lr=&as_filetype=&ft=i&as_sitesearch=&as_qdr=all&as_rights=&as_occt=any&cr=&as_nlo=&as_nhi=&safe=images",
		"ValidText": "검색 도움말|개인정보 보호센터|support.google. | google.timers.load | webcache.googleusercontent",
		"IsValid": "1",
		"DateValidated": "2015-02-14T12:15:00"
	},
	{
		"EngineID": "170",
		"LanguageID": "1161",
		"Name": ".com.kw (Kuwait)",
		"DateCreated": "2010-09-08T14:40:34.160",
		"ContryID": "119",
		"QueryURL": "https://www.google.com.kw/search?hl=ar&q={0}&as_epq=&as_oq=&as_eq=&num=100&lr=&as_filetype=&ft=i&as_sitesearch=&as_qdr=all&as_rights=&as_occt=any&cr=&as_nlo=&as_nhi=&safe=images",
		"ValidText": "كل ما تحب معرفته عن Google&rlm; هنا|البرنامج الإعلاني|كل شيء|support.google. | google.timers.load | webcache.googleusercontent",
		"IsValid": "1",
		"DateValidated": "2015-02-14T12:15:00"
	},
	{
		"EngineID": "171",
		"LanguageID": "1640",
		"Name": ".kz (Kazakhstan)",
		"DateCreated": "2010-09-08T14:41:19.420",
		"ContryID": "114",
		"QueryURL": "https://www.google.kz/search?hl=kk&q={0}&as_epq=&as_oq=&as_eq=&num=100&lr=&as_filetype=&ft=i&as_sitesearch=&as_qdr=all&as_rights=&as_occt=any&cr=&as_nlo=&as_nhi=&safe=images",
		"ValidText": "Іздеу жайында кеңестер|Google туралы барлық нәрсе|Google&nbsp;Home|support.google. | google.timers.load | webcache.googleusercontent",
		"IsValid": "1",
		"DateValidated": "2015-02-14T12:15:00"
	},
	{
		"EngineID": "172",
		"LanguageID": "1652",
		"Name": ".la (Laos)",
		"DateCreated": "2010-09-08T14:42:02.483",
		"ContryID": "121",
		"QueryURL": "https://www.google.la/search?hl=lo&q={0}&as_epq=&as_oq=&as_eq=&num=100&lr=&as_filetype=&ft=i&as_sitesearch=&as_qdr=all&as_rights=&as_occt=any&cr=&as_nlo=&as_nhi=&safe=images",
		"ValidText": "ຄຳແນະນຳໃນການຊອກຫາ|ສົ່ງຄຳຕິຊົມຫາພວກເຮົາ|Google&nbsp;Home|support.google. | google.timers.load | webcache.googleusercontent",
		"IsValid": "1",
		"DateValidated": "2015-02-14T12:16:00"
	},
	{
		"EngineID": "173",
		"LanguageID": "1161",
		"Name": ".com.lb (Lebanon)",
		"DateCreated": "2010-09-08T14:42:40.120",
		"ContryID": "123",
		"QueryURL": "https://www.google.com.lb/search?hl=ar&q={0}&as_epq=&as_oq=&as_eq=&num=100&lr=&as_filetype=&ft=i&as_sitesearch=&as_qdr=all&as_rights=&as_occt=any&cr=&as_nlo=&as_nhi=&safe=images",
		"ValidText": "Gmail|كل شيء|كل ما تحب معرفته عن Google&rlm; هنا|support.google. | google.timers.load | webcache.googleusercontent",
		"IsValid": "1",
		"DateValidated": "2015-02-14T12:16:00"
	},
	{
		"EngineID": "174",
		"LanguageID": "1421",
		"Name": ".lv (Latvia)",
		"DateCreated": "2010-09-08T14:43:28.997",
		"ContryID": "122",
		"QueryURL": "https://www.google.lv/search?hl=lv&q={0}&as_epq=&as_oq=&as_eq=&num=100&lr=&as_filetype=&ft=i&as_sitesearch=&as_qdr=all&as_rights=&as_occt=any&cr=&as_nlo=&as_nhi=&safe=images",
		"ValidText": "Reklamēšanas programma|Meklēšanas&nbsp;palīgs|Google&nbsp;Sākumlapa|Viss par Google|support.google. | google.timers.load | webcache.googleusercontent",
		"IsValid": "1",
		"DateValidated": "2015-02-14T12:16:00"
	},
	{
		"EngineID": "175",
		"LanguageID": "1653",
		"Name": ".lt (Lithuanian)",
		"DateCreated": "2010-09-08T14:44:36.173",
		"ContryID": "128",
		"QueryURL": "https://www.google.lt/search?hl=lt&q={0}&as_epq=&as_oq=&as_eq=&num=100&lr=&as_filetype=&ft=i&as_sitesearch=&as_qdr=all&as_rights=&as_occt=any&cr=&as_nlo=&as_nhi=&safe=images",
		"ValidText": "Patarimai kaip ieškoti|Privatumas|„Google“&nbsp;Pagrindinis puslapis|Pateikite atsiliepimą|support.google. | google.timers.load | webcache.googleusercontent",
		"IsValid": "1",
		"DateValidated": "2015-02-14T12:16:00"
	},
	{
		"EngineID": "176",
		"LanguageID": "1553",
		"Name": ".pt (Protugal)",
		"DateCreated": "2010-09-08T14:45:18.923",
		"ContryID": "178",
		"QueryURL": "https://www.google.pt/search?hl=pt&q={0}&as_epq=&as_oq=&as_eq=&num=100&lr=&as_filetype=&ft=i&as_sitesearch=&as_qdr=all&as_rights=&as_occt=any&cr=&as_nlo=&as_nhi=&safe=images",
		"ValidText": "Página inicial do&nbsp;Google|Privacidade|Soluções de publicidade|support.google. | google.timers.load | webcache.googleusercontent",
		"IsValid": "1",
		"DateValidated": "2015-02-14T12:16:00"
	},
	{
		"EngineID": "177",
		"LanguageID": "1640",
		"Name": ".com.tr (Turkey)",
		"DateCreated": "2010-09-08T14:46:07.563",
		"ContryID": "226",
		"QueryURL": "https://www.google.com.tr/search?hl=tr&q={0}&as_epq=&as_oq=&as_eq=&num=100&lr=&as_filetype=&ft=i&as_sitesearch=&as_qdr=all&as_rights=&as_occt=any&cr=&as_nlo=&as_nhi=&safe=images",
		"ValidText": "Google&nbsp;Ana Sayfa|Bize görüşlerinizi bildirin|Her şey|support.google. | google.timers.load | webcache.googleusercontent",
		"IsValid": "1",
		"DateValidated": "2015-02-14T12:16:00"
	},
	{
		"EngineID": "178",
		"LanguageID": "1616",
		"Name": ".co.cr (Costa Rica)",
		"DateCreated": "2010-09-08T14:47:03.870",
		"ContryID": "54",
		"QueryURL": "https://www.google.co.cr/search?hl=es&q={0}&as_epq=&as_oq=&as_eq=&num=100&lr=&as_filetype=&ft=i&as_sitesearch=&as_qdr=all&as_rights=&as_occt=any&cr=&as_nlo=&as_nhi=&safe=images",
		"ValidText": "Página principal de&nbsp;Google|Enviar comentarios|Privacidad|Todo|support.google. | google.timers.load | webcache.googleusercontent",
		"IsValid": "1",
		"DateValidated": "2015-02-14T12:16:00"
	},
	{
		"EngineID": "179",
		"LanguageID": "1560",
		"Name": ".md (Moldoveneasca)",
		"DateCreated": "2013-04-26T17:09:22.887",
		"ContryID": "145",
		"QueryURL": "https://www.google.md/search?hl=ro&q={0}&as_epq=&as_oq=&as_eq=&num=100&lr=&as_filetype=&ft=i&as_sitesearch=&as_qdr=all&as_rights=&as_occt=any&cr=&as_nlo=&as_nhi=&safe=images",
		"ValidText": "Totul despre Google|support.google. | google.timers.load | webcache.googleusercontent",
		"IsValid": "1",
		"DateValidated": "2015-02-14T12:16:00"
	},
	{
		"EngineID": "231",
		"LanguageID": "1700",
		"Name": ".com.ua (Ukraine)",
		"DateCreated": "2011-03-30T22:42:45.363",
		"ContryID": "231",
		"QueryURL": "https://www.google.com.ua/search?hl=uk&q={0}&as_epq=&as_oq=&as_eq=&num=100&lr=&as_filetype=&ft=i&as_sitesearch=&as_qdr=all&as_rights=&as_occt=any&cr=&as_nlo=&as_nhi=&safe=images",
		"ValidText": "Як&nbsp;шукати|Рекламні програми|Google&nbsp;Домашня сторінка|support.google. | google.timers.load | webcache.googleusercontent",
		"IsValid": "1",
		"DateValidated": "2015-02-14T12:16:00"
	},
	{
		"EngineID": "250",
		"LanguageID": "1",
		"Name": ".co.bw (Botswana)",
		"DateCreated": "2013-09-18T18:28:33.010",
		"ContryID": "30",
		"QueryURL": "https://www.google.co.bw/search?hl=en&q={0}&as_epq=&as_oq=&as_eq=&num=100&lr=&as_filetype=&ft=i&as_sitesearch=&as_qdr=all&as_rights=&as_occt=any&cr=&as_nlo=&as_nhi=&safe=images",
		"ValidText": "Botswana|support.google. | google.timers.load | webcache.googleusercontent",
		"IsValid": "1",
		"DateValidated": "2015-02-14T12:16:00"
	},
	{
		"EngineID": "251",
		"LanguageID": "1",
		"Name": ".co.za (South Africa)",
		"DateCreated": "2013-09-18T18:28:33.033",
		"ContryID": "205",
		"QueryURL": "https://www.google.co.za/search?hl=en&q={0}&as_epq=&as_oq=&as_eq=&num=100&lr=&as_filetype=&ft=i&as_sitesearch=&as_qdr=all&as_rights=&as_occt=any&cr=&as_nlo=&as_nhi=&safe=images",
		"ValidText": "google|support.google. | google.timers.load | webcache.googleusercontent",
		"IsValid": "1",
		"DateValidated": "2015-02-14T12:16:00"
	},
	{
		"EngineID": "252",
		"LanguageID": "1",
		"Name": ".co.zm (Zambia)",
		"DateCreated": "2013-09-18T18:28:33.043",
		"ContryID": "246",
		"QueryURL": "https://www.google.co.zm/search?hl=en&q={0}&as_epq=&as_oq=&as_eq=&num=100&lr=&as_filetype=&ft=i&as_sitesearch=&as_qdr=all&as_rights=&as_occt=any&cr=&as_nlo=&as_nhi=&safe=images",
		"ValidText": "Zambia|support.google. | google.timers.load | webcache.googleusercontent",
		"IsValid": "1",
		"DateValidated": "2015-02-14T12:17:00"
	},
	{
		"EngineID": "253",
		"LanguageID": "1",
		"Name": ".co.zw (Zimbabwe)",
		"DateCreated": "2013-09-18T18:28:33.050",
		"ContryID": "247",
		"QueryURL": "https://www.google.co.zw/search?hl=en&q={0}&as_epq=&as_oq=&as_eq=&num=100&lr=&as_filetype=&ft=i&as_sitesearch=&as_qdr=all&as_rights=&as_occt=any&cr=&as_nlo=&as_nhi=&safe=images",
		"ValidText": "Zimbabwe|support.google. | google.timers.load | webcache.googleusercontent",
		"IsValid": "1",
		"DateValidated": "2015-02-14T12:17:00"
	},
	{
		"EngineID": "254",
		"LanguageID": "1603",
		"Name": ".sk (Slovakia)",
		"DateCreated": "2014-10-29T17:11:03.943",
		"ContryID": "201",
		"QueryURL": "https://www.google.sk/search?hl=en&q={0}&as_epq=&as_oq=&as_eq=&num=100&lr=&as_filetype=&ft=i&as_sitesearch=&as_qdr=all&as_rights=&as_occt=any&cr=&as_nlo=&as_nhi=&safe=images",
		"ValidText": "Slovensko|support.google. | google.timers.load | webcache.googleusercontent",
		"IsValid": "1",
		"DateValidated": "2015-02-14T12:17:00"
	}
]